hyrule_builder/__init__.py
hyrule_builder/__main__.py
hyrule_builder/__version__.py
hyrule_builder/builder.py
hyrule_builder/rstb_main.py
hyrule_builder/sarc_main.py
hyrule_builder/unbuilder.py
hyrule_builder/data/switch/rstb.json
hyrule_builder/data/wiiu/rstb.json
hyrule_builder-0.7.4.dist-info/LICENSE
hyrule_builder-0.7.4.dist-info/METADATA
hyrule_builder-0.7.4.dist-info/WHEEL
hyrule_builder-0.7.4.dist-info/entry_points.txt
hyrule_builder-0.7.4.dist-info/top_level.txt
hyrule_builder-0.7.4.dist-info/RECORD
