Metadata-Version: 2.1
Name: hyrule-builder
Version: 0.7.4
Summary: A mod builder/unbuilder for The Legend of Zelda: Breath of the Wild
Home-page: https://github.com/NiceneNerd/Hyrule-Builder
Author: NiceneNerd
Author-email: macadamiadaze@gmail.com
License: UNKNOWN
Platform: UNKNOWN
Classifier: Development Status :: 3 - Alpha
Classifier: License :: OSI Approved :: GNU General Public License v3 or later (GPLv3+)
Classifier: Programming Language :: Python :: 3 :: Only
Requires-Python: >=3.7
Requires-Dist: botw-utils (>=0.2.3)
Requires-Dist: oead (~=1.2.0)
Requires-Dist: pymsyt (<0.4.0,>=0.3.2)
Requires-Dist: rstb (>=1.2.1)
Requires-Dist: xxhash (~=1.4.3)
